icon_gen/__init__.py
icon_gen_ai/__init__.py
icon_gen_ai/__main__.py
icon_gen_ai/cli.py
icon_gen_ai/generator.py
icon_gen_ai/ai/__init__.py
icon_gen_ai/ai/anthropic_provider.py
icon_gen_ai/ai/assistant.py
icon_gen_ai/ai/base.py
icon_gen_ai/ai/huggingface_provider.py
icon_gen_ai/ai/openai_provider.py
icon_gen_ai/ai/prompts.py
icon_gen_ai/animation/__init__.py
icon_gen_ai/animation/animator.py
icon_gen_ai/animation/webp_exporter.py
icon_gen_ai-0.4.10.dist-info/licenses/LICENSE
icon_gen_ai-0.4.10.dist-info/METADATA
icon_gen_ai-0.4.10.dist-info/WHEEL
icon_gen_ai-0.4.10.dist-info/entry_points.txt
icon_gen_ai-0.4.10.dist-info/top_level.txt
icon_gen_ai-0.4.10.dist-info/RECORD
