Metadata-Version: 2.4
Name: icon-gen-ai
Version: 0.4.10
Summary: Generate pixel-perfect icons from Iconify, direct URLs, and local files—with animation support and exports to PNG, SVG, WebP, and ICO
Author: Yauheniya Varabyova
License-Expression: MIT
Project-URL: Documentation, https://yauheniya-ai.github.io/icon-gen-ai/
Project-URL: Playground UI, https://yauheniya-ai.github.io/icon-gen-ai-playground/
Project-URL: Playground API, https://huggingface.co/spaces/Yauheniya/icon-gen-ai-api
Project-URL: Repository, https://github.com/yauheniya-ai/icon-gen-ai
Keywords: icons,logos,iconify,svg,png,webp,ico
Requires-Python: >=3.10
License-File: LICENSE
Requires-Dist: requests<3.0,>=2.31.0
Requires-Dist: urllib3<3.0,>=2.0
Requires-Dist: pillow<11.0,>=10.0.0
Requires-Dist: cairosvg<3.0,>=2.7.0
Requires-Dist: click<9.0,>=8.1.0
Provides-Extra: ai
Requires-Dist: openai>=1.0.0; extra == "ai"
Requires-Dist: anthropic>=0.18.0; extra == "ai"
Requires-Dist: huggingface-hub>=1.3.1; extra == "ai"
Requires-Dist: python-dotenv>=1.0.0; extra == "ai"
Dynamic: license-file
